Workbook

Sheet Ringkasan & Panduan
A1: PEMETAAN CHART OF ACCOUNTS (COA) STANDAR MANUFAKTUR
A2: Sistem Akuntansi Terintegrasi Manufaktur & Modul ERPNext/Frappe | Versi 1.0 (2026)
A4: TOTAL STRUKTUR COA | C4: AKUN PERSEDIAAN & COSTING | E4: KATEGORI UTAMA
A5: =COUNTA('Chart of Accounts'!A6:A70) | C5: =COUNTIF('Chart of Accounts'!E6:E70, "Stock") + COUNTIF('Chart of Accounts'!E6:E70, "Cost of Goods Sold") | E5: 7
A7: 1. DESKRIPSI & TUJUAN MODEL
A8: Fungsi Utama | B8: Menyediakan hierarki akun akuntansi standar khusus untuk entitas manufaktur yang mencakup akumulasi biaya bahan baku, tenaga kerja langsung, overhead pabrik (BOP), persediaan 3-tahap (Bahan Baku, WIP, Barang Jadi), dan HPP.
A9: Kesesuaian ERPNext | B9: Dirancang agar sejalan secara presisi dengan ERPNext Root Types (Asset, Liability, Equity, Income, Expense) serta atribut Account Type (Stock, Cost of Goods Sold, Warehouse Clearing, dll.).
A10: Tingkat Kedalaman | B10: Terdiri dari 4 Level Hierarki: Level 1 (Kategori Utama), Level 2 (Sub-Kelompok Utama), Level 3 (Akun Induk/Group), dan Level 4 (Akun Detail Transaksi).
A12: 2. ELEMEN KUNCI COA SPESIFIK MANUFAKTUR
A13: Komponen Akun | B13: Kode Akun Ref | C13: Tipe ERPNext | D13: Fungsi Akuntansi Manufaktur
A14: Persediaan Bahan Baku | B14: 11310 | C14: Stock | D14: Menampung nilai persediaan material mentah yang dibeli dari supplier sebelum dirilis ke proses produksi.
A15: Persediaan Barang Dalam Proses (WIP) | B15: 11330 | C15: Stock | D15: Menampung akumulasi biaya bahan baku, BTKL, dan BOP yang sedang mengendap dalam saluran produksi (Floor).
A16: Persediaan Barang Jadi (Finished Goods) | B16: 11340 | C16: Stock | D16: Menampung nilai produk akhir hasil pabrikasi yang siap dijual kepada pelanggan.
A17: Biaya Bahan Baku Langsung (BBBL) | B17: 51100 | C17: Cost of Goods Sold | D17: Mencatat pemakaian langsung bahan baku utama yang membentuk fisik produk jadi.
A18: Biaya Tenaga Kerja Langsung (BTKL) | B18: 52100 | C18: Cost of Goods Sold | D18: Mencatat upah buruh, operator mesin, dan teknisi lantai produksi yang berhubungan langsung dengan pembuatan produk.
A19: Biaya Overhead Pabrik (BOP) | B19: 53000-53600 | C19: Cost of Goods Sold / Expense | D19: Menampung biaya tidak langsung pabrik: bahan penolong, listrik pabrik, penyusutan mesin, & gaji supervisor.
A20: Variansi Produksi & WIP Clearing | B20: 54100 | C20: Cost of Goods Sold | D20: Menampung selisih antara standar cost vs actual cost pada BOM (Bill of Materials) & Work Orders.
A22: 3. LEGEND ABNOMALITAS & PEWARNAAN FORMAT
A23: Header / Sub-Judul Kategori | B23: Level 1 & Kategori Utama Akun (Aset, Kewajiban, Ekuitas, Pendapatan, HPP, Beban)
A24: Akun Induk / Group (Is Group = Ya) | B24: Akun Penampung Sub-Kelompok (Tidak digunakan untuk posting transaksi langsung)
A25: Akun Detail Transaksi (Is Group = Tidak) | B25: Akun Buku Besar (Ledger) aktif untuk jurnal transaksi operasional sehari-hari
A26: Atribut / Output Kalkulasi | B26: Cell yang memuat formula perhitungan rasio, akumulasi saldo, atau agregasi data

Sheet Chart of Accounts
A1: STRUKTUR LENGKAP CHART OF ACCOUNTS (COA) MANUFAKTUR
A2: Daftar Akun Standar Industri Pengolahan & Pemetaan ERPNext Root/Account Type
A5: Kode Akun | B5: Nama Akun (Indonesia / English) | C5: Level | D5: Kategori Utama (Root) | E5: Tipe Akun ERPNext | F5: Is Group | G5: Saldo Normal | H5: Fungsi Operasional & Perlakuan Akuntansi
A6: 10000 | B6: ASET (ASSETS) | C6: 1 | D6: Aset | E6: Asset | F6: Ya | G6: Debet | H6: Kelompok Utama Aset Perusahaan Manufaktur
A7: 11000 | B7: Aset Lancar (Current Assets) | C7: 2 | D7: Aset | E7: Asset | F7: Ya | G7: Debet | H7: Sub-Kelompok Aset Lancar
A8: 11100 | B8: Kas & Bank (Cash & Bank) | C8: 3 | D8: Aset | E8: Cash | F8: Ya | G8: Debet | H8: Grup Akun Kas dan Rebound Perbankan
A9: 11110 | B9: Kas Kecil Pabrik (Factory Petty Cash) | C9: 4 | D9: Aset | E9: Cash | F9: Tidak | G9: Debet | H9: Kas tunai pengeluaran operasional kecil di area pabrik
A10: 11120 | B10: Bank Utama IDR (Main Bank Account) | C10: 4 | D10: Aset | E10: Bank | F10: Tidak | G10: Debet | H10: Rekening bank operasional penerimaan & pembayaran supplier
A11: 11200 | B11: Piutang Usaha (Accounts Receivable) | C11: 3 | D11: Aset | E11: Receivable | F11: Ya | G11: Debet | H11: Grup Piutang Penjualan Barang Jadi
A12: 11210 | B12: Piutang Dagang Pelanggan (Trade Receivables) | C12: 4 | D12: Aset | E12: Receivable | F12: Tidak | G12: Debet | H12: Tagihan atas penjualan produk jadi kepada distributor/customer
A13: 11220 | B13: Cadangan Kerugian Piutang (Allowance for Bad Debts) | C13: 4 | D13: Aset | E13: Receivable | F13: Tidak | G13: Kredit | H13: Kontra akun pengurangan nilai piutang tak tertagih
A14: 11300 | B14: Persediaan Manufaktur (Manufacturing Inventory) | C14: 3 | D14: Aset | E14: Stock | F14: Ya | G14: Debet | H14: Grup Utama Persediaan 3-Tahap Manufaktur
A15: 11310 | B15: Persediaan Bahan Baku (Raw Materials Inventory) | C15: 4 | D15: Aset | E15: Stock | F15: Tidak | G15: Debet | H15: Bahan utama mentah yang belum diproses
A16: 11320 | B16: Persediaan Bahan Penolong & Pengemas (Auxiliary & Packaging) | C16: 4 | D16: Aset | E16: Stock | F16: Tidak | G16: Debet | H16: Material pembantu produksi & kemasan produk
A17: 11330 | B17: Persediaan Barang Dalam Proses (Work-in-Progress / WIP) | C17: 4 | D17: Aset | E17: Stock | F17: Tidak | G17: Debet | H17: Nilai barang yang masih dalam lini pabrikasi
... A77: 72000 | B77: Beban Bunga Pinjaman & Administrasi Bank (Interest Expense) | C77: 2 | D77: Lain-lain | E77: Expense | F77: Tidak | G77: Debet | H77: Beban bunga kredit bank & biaya adm perbankan

Sheet Alur Jurnal Manufaktur
A1: PEMETAAN ALUR JURNAL AKUNTANSI MANUFAKTUR & WORK ORDER
A2: Panduan Transaksi Siklus Pemrosesan Bahan Baku hingga Pengakuan HPP Penjualan di ERPNext
A5: Tahap Alur Produksi | B5: Nama Transaksi ERPNext | C5: Skenario Operasional Pabrik | D5: Akun Debet (+) | E5: Akun Kredit (-) | F5: Pengaruh pada Laporan Keuangan | G5: Dokumen Terkait
A6: 1. Pembelian Bahan Baku | B6: Purchase Receipt / Invoice | C6: Penerimaan bahan baku mentah dari vendor ke gudang penyimpanan. | D6: 11310 - Persediaan Bahan Baku | E6: 21110 - Utang Dagang Pemasok | F6: Aset Persediaan (+) & Kewajiban Utang (+) | G6: Purchase Order (PO) & GRN
A7: 2. Pengeluaran Bahan ke Produksi | B7: Stock Entry (Issue to WIP) | C7: Transfer bahan baku mentah dari gudang utama ke lantai pabrikasi (Work Order). | D7: 11330 - Persediaan Barang Dalam Proses (WIP) | E7: 11310 - Persediaan Bahan Baku | F7: Aset WIP (+) & Aset Bahan Baku (-) | G7: Material Issue / Work Order
A8: 3. Alokasi BTKL & Overhead | B8: Timesheet / Labor & Overhead Entry | C8: Pembebanan gaji buruh produksi & utilitas pabrik ke dalam alur produksi berjalan. | D8: 11330 - Persediaan Barang Dalam Proses (WIP) | E8: 21210 - Utang Gaji Buruh Pabrik / 21220 - Akrual Utilitas | F8: Aset WIP (+) & Kewajiban Gaji/Beban (+) | G8: Job Card / Timesheet / Direct Expense
A9: 4. Penyelesaian Barang Jadi | B9: Stock Entry (Manufacture / Finish) | C9: Penyelesaian proses produksi & penyerahan produk jadi dari lantai pabrik ke gudang FG. | D9: 11340 - Persediaan Barang Jadi (Finished Goods) | E9: 11330 - Persediaan Barang Dalam Proses (WIP) | F9: Aset Barang Jadi (+) & Aset WIP (-) | G9: Work Order Completion / Production Entry
A10: 5. Penjualan & Pengiriman Produk | B10: Sales Invoice & Delivery Note | C10: Penjualan produk jadi kepada pelanggan distributor dan pengakuan HPP. | D10: 11210 - Piutang Dagang / 11120 - Bank 51100 - Pemakaian BBBL (HPP) | E10: 41100 - Penjualan Barang Jadi 11340 - Persediaan Barang Jadi | F10: Pendapatan Penjualan (+), Aset Piutang (+), HPP (+), Persediaan FG (-) | G10: Delivery Note & Sales Invoice
A11: 6. Penjualan Scrap / Sisa Bahan | B11: Stock Entry / Miscellaneous Invoice | C11: Penjualan sisa potongan material/limbah pabrikasi yang memiliki nilai jual. | D11: 11110 - Kas Kecil / 11210 - Piutang | E11: 43000 - Penjualan Scrap / Hasil Sampingan | F11: Aset Kas/Piutang (+) & Pendapatan Lain (+) | G11: Sales Invoice Scrap

Sheet Statistik & Distribusi
A1: RINGKASAN STATISTIK & DISTRIBUSI AKUN MANUFAKTUR
A2: Analisis Agregat Jumlah Akun, Proporsi Kategori, & Kesiapan Modul Akuntansi ERPNext
A5: DISTRIBUSI AKUN PER KATEGORI UTAMA
A6: Kategori Utama (Root) | B6: Jumlah Akun Group | C6: Jumlah Akun Detail (Ledger) | D6: Total Akun
A7: Aset | B7: =COUNTIFS('Chart of Accounts'!$D$6:$D$70, "Aset", 'Chart of Accounts'!$F$6:$F$70, "Ya") | C7: =COUNTIFS('Chart of Accounts'!$D$6:$D$70, "Aset", 'Chart of Accounts'!$F$6:$F$70, "Tidak") | D7: =SUM(B7:C7)
A8: Kewajiban | B8: =COUNTIFS('Chart of Accounts'!$D$6:$D$70, "Kewajiban", 'Chart of Accounts'!$F$6:$F$70, "Ya") | C8: =COUNTIFS('Chart of Accounts'!$D$6:$D$70, "Kewajiban", 'Chart of Accounts'!$F$6:$F$70, "Tidak") | D8: =SUM(B8:C8)
A9: Ekuitas | B9: =COUNTIFS('Chart of Accounts'!$D$6:$D$70, "Ekuitas", 'Chart of Accounts'!$F$6:$F$70, "Ya") | C9: =COUNTIFS('Chart of Accounts'!$D$6:$D$70, "Ekuitas", 'Chart of Accounts'!$F$6:$F$70, "Tidak") | D9: =SUM(B9:C9)
A10: Pendapatan | B10: =COUNTIFS('Chart of Accounts'!$D$6:$D$70, "Pendapatan", 'Chart of Accounts'!$F$6:$F$70, "Ya") | C10: =COUNTIFS('Chart of Accounts'!$D$6:$D$70, "Pendapatan", 'Chart of Accounts'!$F$6:$F$70, "Tidak") | D10: =SUM(B10:C10)
A11: Harga Pokok Penjualan (HPP) | B11: =COUNTIFS('Chart of Accounts'!$D$6:$D$70, "HPP", 'Chart of Accounts'!$F$6:$F$70, "Ya") | C11: =COUNTIFS('Chart of Accounts'!$D$6:$D$70, "HPP", 'Chart of Accounts'!$F$6:$F$70, "Tidak") | D11: =SUM(B11:C11)
A12: Beban Operasional | B12: =COUNTIFS('Chart of Accounts'!$D$6:$D$70, "Beban Operasional", 'Chart of Accounts'!$F$6:$F$70, "Ya") | C12: =COUNTIFS('Chart of Accounts'!$D$6:$D$70, "Beban Operasional", 'Chart of Accounts'!$F$6:$F$70, "Tidak") | D12: =SUM(B12:C12)
A13: Pendapatan/Beban Lain-lain | B13: =COUNTIFS('Chart of Accounts'!$D$6:$D$70, "Lain-lain", 'Chart of Accounts'!$F$6:$F$70, "Ya") | C13: =COUNTIFS('Chart of Accounts'!$D$6:$D$70, "Lain-lain", 'Chart of Accounts'!$F$6:$F$70, "Tidak") | D13: =SUM(B13:C13)
A14: TOTAL KESELURUHAN | B14: =SUM(B7:B13) | C14: =SUM(C7:C13) | D14: =SUM(D7:D13)
A17: REKAPITULASI BERDASARKAN LEVEL HIERARKI
A18: Tingkat Hierarki | B18: Penjelasan Level | C18: Jumlah Akun | D18: Persentase (%)
A19: Level 1 | B19: Level 1 - Kategori Utama Root | C19: =COUNTIF('Chart of Accounts'!$C$6:$C$70, 1) | D19: =C19/$D$14
A20: Level 2 | B20: Level 2 - Sub-Kelompok Utama | C20: =COUNTIF('Chart of Accounts'!$C$6:$C$70, 2) | D20: =C20/$D$14
A21: Level 3 | B21: Level 3 - Akun Induk / Group | C21: =COUNTIF('Chart of Accounts'!$C$6:$C$70, 3) | D21: =C21/$D$14
A22: Level 4 | B22: Level 4 - Akun Detail Transaksi | C22: =COUNTIF('Chart of Accounts'!$C$6:$C$70, 4) | D22: =C22/$D$14
